<?xml version="1.0" encoding="utf-8"?>
<odoo>
    <record id="view_form_add_application" model="ir.ui.view">
        <field name="name">Applications</field>
        <field name="model">sis.application</field>
        <field name="arch" type="xml">
            <form>
                <header>
                    <button name="button_accept" string="Accept" class="oe_highlight" type="object"
                            attrs="{'invisible':['|',('status','=', 'declined'),('status','=','accepted')]}"/>
                    <button name="button_declined" string="Decline" class="oe_highlight" type="object"
                            attrs="{'invisible':['|',('status','=', 'declined'),('status','=','accepted')]}"/>
                </header>
                <sheet>
                    <group>
                        <h1 style="text-align:center;">Applicant</h1>
                    </group>

                    <group>
                        <h3>Personal Details</h3>
                        <field name="name"/>
                        <field name="surname"/>
                        <field name="dob"/>
                        <field name="gender"/>
                        <field name="address"/>
                        <field name="phone"/>
                        <field name="email"/>
                    </group>
                    <group>
                        <h3>Academic Background</h3>
                        <field name="transcript"/>
                        <field name="highest_qualification"/>
                        <field name="school"/>
                    </group>
                    <group>
                        <h3>Programme Application</h3>
                        <field name="programme"/>
                    </group>
                    <group>
                        <h3>Set Your Password To Log In</h3>
                        <field name="password"/>
                    </group>
                    <group>
                        <h3>Application Status</h3>
                        <field name="status"/>
                    </group>
                </sheet>
            </form>
        </field>
    </record>

    <record id="view_tree_applications" model="ir.ui.view">
        <field name="name">Programme List View</field>
        <field name="model">sis.application</field>
        <field name="arch" type="xml">
            <tree>
                <field name="name"/>
                <field name="surname"/>
                <field name="dob"/>
                <field name="gender"/>
                <field name="id"/>
                <field name="programme"/>
                <field name="transcript"/>
                <field name="address"/>
                <field name="phone"/>
                <field name="email"/>
                <field name="highest_qualification"/>
                <field name="school"/>
                <field name="status"/>
            </tree>
        </field>
    </record>
</odoo>
